flask_resources/__init__.py
flask_resources/config.py
flask_resources/content_negotiation.py
flask_resources/context.py
flask_resources/errors.py
flask_resources/resources.py
flask_resources/responses.py
flask_resources/deserializers/__init__.py
flask_resources/deserializers/base.py
flask_resources/deserializers/json.py
flask_resources/parsers/__init__.py
flask_resources/parsers/base.py
flask_resources/parsers/body.py
flask_resources/parsers/decorators.py
flask_resources/parsers/schema.py
flask_resources/serializers/__init__.py
flask_resources/serializers/base.py
flask_resources/serializers/csv.py
flask_resources/serializers/json.py
flask_resources/serializers/simple.py
flask_resources-1.2.0.dist-info/AUTHORS.rst
flask_resources-1.2.0.dist-info/LICENSE
flask_resources-1.2.0.dist-info/METADATA
flask_resources-1.2.0.dist-info/WHEEL
flask_resources-1.2.0.dist-info/top_level.txt
flask_resources-1.2.0.dist-info/RECORD
