Metadata-Version: 2.1
Name: flask-resources
Version: 1.2.0
Summary: "Flask Resources module to create REST APIs."
Home-page: https://github.com/inveniosoftware/flask-resources
Author: CERN
Author-email: info@inveniosoftware.org
License: MIT
Keywords: flask TODO
Platform: any
Classifier: Development Status :: 3 - Alpha
Requires-Python: >=3.7
Requires-Dist: Flask >=1.1.4
Requires-Dist: marshmallow ~=3.0
Requires-Dist: speaklater <2.0,>=1.3
Provides-Extra: tests
Requires-Dist: check-manifest >=0.42 ; extra == 'tests'
Requires-Dist: coverage <6,>=5.3 ; extra == 'tests'
Requires-Dist: pytest <8,>=7 ; extra == 'tests'
Requires-Dist: pytest-black >=0.3.0 ; extra == 'tests'
Requires-Dist: pytest-cov >=2.10.1 ; extra == 'tests'
Requires-Dist: pytest-flask >=1.0.0 ; extra == 'tests'
Requires-Dist: pytest-isort >=1.2.0 ; extra == 'tests'
Requires-Dist: pytest-mock >=1.6.0 ; extra == 'tests'
Requires-Dist: pytest-pydocstyle >=2.2.3 ; extra == 'tests'
Requires-Dist: Sphinx >=4.5.0 ; extra == 'tests'
